<?xml version="1.0" ?><Document doc_id="141225" doc_name="141225_British_FTSE_index_reaches_one-year_high,_other_European_markets_rise" lang="nl" url="http://en.wikinews.org/wiki/British_FTSE_index_reaches_one-year_high,_other_European_markets_rise">
  <token number="0" sentence="0" t_id="1">De</token>
  <token number="1" sentence="0" t_id="2">FTSE-index</token>
  <token number="2" sentence="0" t_id="3">bereikt</token>
  <token number="3" sentence="0" t_id="4">hoogste</token>
  <token number="4" sentence="0" t_id="5">punt</token>
  <token number="5" sentence="0" t_id="6">in</token>
  <token number="6" sentence="0" t_id="7">een</token>
  <token number="7" sentence="0" t_id="8">jaar</token>
  <token number="8" sentence="0" t_id="9">,</token>
  <token number="9" sentence="0" t_id="10">andere</token>
  <token number="10" sentence="0" t_id="11">Europese</token>
  <token number="11" sentence="0" t_id="12">beurzen</token>
  <token number="12" sentence="0" t_id="13">stijgen</token>
  <token number="13" sentence="1" t_id="14">12-Oct-09</token>
  <token number="14" sentence="2" t_id="15">De</token>
  <token number="15" sentence="2" t_id="16">Britse</token>
  <token number="16" sentence="2" t_id="17">beursindex</token>
  <token number="17" sentence="2" t_id="18">FTSE</token>
  <token number="18" sentence="2" t_id="19">100</token>
  <token number="19" sentence="2" t_id="20">sloot</token>
  <token number="20" sentence="2" t_id="21">maandag</token>
  <token number="21" sentence="2" t_id="22">op</token>
  <token number="22" sentence="2" t_id="23">het</token>
  <token number="23" sentence="2" t_id="24">hoogste</token>
  <token number="24" sentence="2" t_id="25">punt</token>
  <token number="25" sentence="2" t_id="26">in</token>
  <token number="26" sentence="2" t_id="27">een</token>
  <token number="27" sentence="2" t_id="28">jaar</token>
  <token number="28" sentence="2" t_id="29">nadat</token>
  <token number="29" sentence="2" t_id="30">betere</token>
  <token number="30" sentence="2" t_id="31">grondstoffenprijzen</token>
  <token number="31" sentence="2" t_id="32">werden</token>
  <token number="32" sentence="2" t_id="33">aangekondigd</token>
  <token number="33" sentence="2" t_id="34">.</token>
  <token number="0" sentence="3" t_id="35">De</token>
  <token number="1" sentence="3" t_id="36">index</token>
  <token number="2" sentence="3" t_id="37">steeg</token>
  <token number="3" sentence="3" t_id="38">48,3</token>
  <token number="4" sentence="3" t_id="39">punten</token>
  <token number="5" sentence="3" t_id="40">of</token>
  <token number="6" sentence="3" t_id="41">0,9</token>
  <token number="7" sentence="3" t_id="42">%</token>
  <token number="8" sentence="3" t_id="43">en</token>
  <token number="9" sentence="3" t_id="44">sloot</token>
  <token number="10" sentence="3" t_id="45">de</token>
  <token number="11" sentence="3" t_id="46">dag</token>
  <token number="12" sentence="3" t_id="47">af</token>
  <token number="13" sentence="3" t_id="48">op</token>
  <token number="14" sentence="3" t_id="49">5.210,17</token>
  <token number="15" sentence="3" t_id="50">,</token>
  <token number="16" sentence="3" t_id="51">wat</token>
  <token number="17" sentence="3" t_id="52">niet</token>
  <token number="18" sentence="3" t_id="53">meer</token>
  <token number="19" sentence="3" t_id="54">is</token>
  <token number="20" sentence="3" t_id="55">gebeurd</token>
  <token number="21" sentence="3" t_id="56">sinds</token>
  <token number="22" sentence="3" t_id="57">afgelopen</token>
  <token number="23" sentence="3" t_id="58">september</token>
  <token number="24" sentence="3" t_id="59">.</token>
  <token number="0" sentence="4" t_id="60">Old</token>
  <token number="1" sentence="4" t_id="61">Mutual</token>
  <token number="2" sentence="4" t_id="62">verzekeringsmaatschappij</token>
  <token number="3" sentence="4" t_id="63">noteerde</token>
  <token number="4" sentence="4" t_id="64">de</token>
  <token number="5" sentence="4" t_id="65">hoogste</token>
  <token number="6" sentence="4" t_id="66">stijging</token>
  <token number="7" sentence="4" t_id="67">met</token>
  <token number="8" sentence="4" t_id="68">4,6</token>
  <token number="9" sentence="4" t_id="69">%</token>
  <token number="10" sentence="4" t_id="70">en</token>
  <token number="11" sentence="4" t_id="71">bereikte</token>
  <token number="12" sentence="4" t_id="72">daarmee</token>
  <token number="13" sentence="4" t_id="73">de</token>
  <token number="14" sentence="4" t_id="74">hoogste</token>
  <token number="15" sentence="4" t_id="75">koers</token>
  <token number="16" sentence="4" t_id="76">in</token>
  <token number="17" sentence="4" t_id="77">16</token>
  <token number="18" sentence="4" t_id="78">maanden</token>
  <token number="19" sentence="4" t_id="79">.</token>
  <token number="0" sentence="5" t_id="80">Een</token>
  <token number="1" sentence="5" t_id="81">aantal</token>
  <token number="2" sentence="5" t_id="82">economisch</token>
  <token number="3" sentence="5" t_id="83">analisten</token>
  <token number="4" sentence="5" t_id="84">denkt</token>
  <token number="5" sentence="5" t_id="85">dat</token>
  <token number="6" sentence="5" t_id="86">de</token>
  <token number="7" sentence="5" t_id="87">FTSE-index</token>
  <token number="8" sentence="5" t_id="88">de</token>
  <token number="9" sentence="5" t_id="89">rest</token>
  <token number="10" sentence="5" t_id="90">van</token>
  <token number="11" sentence="5" t_id="91">de</token>
  <token number="12" sentence="5" t_id="92">week</token>
  <token number="13" sentence="5" t_id="93">kan</token>
  <token number="14" sentence="5" t_id="94">blijven</token>
  <token number="15" sentence="5" t_id="95">stijgen</token>
  <token number="16" sentence="5" t_id="96">.</token>
  <token number="0" sentence="6" t_id="97">David</token>
  <token number="1" sentence="6" t_id="98">Jones</token>
  <token number="2" sentence="6" t_id="99">,</token>
  <token number="3" sentence="6" t_id="100">hoofd</token>
  <token number="4" sentence="6" t_id="101">marktstrategie</token>
  <token number="5" sentence="6" t_id="102">bij</token>
  <token number="6" sentence="6" t_id="103">IG</token>
  <token number="7" sentence="6" t_id="104">Index</token>
  <token number="8" sentence="6" t_id="105">,</token>
  <token number="9" sentence="6" t_id="106">zei</token>
  <token number="10" sentence="6" t_id="107">dat</token>
  <token number="11" sentence="6" t_id="108">``het</token>
  <token number="12" sentence="6" t_id="109">volgende</token>
  <token number="13" sentence="6" t_id="110">FTSE-doel</token>
  <token number="14" sentence="6" t_id="111">voor</token>
  <token number="15" sentence="6" t_id="112">de</token>
  <token number="16" sentence="6" t_id="113">korte</token>
  <token number="17" sentence="6" t_id="114">termijn</token>
  <token number="18" sentence="6" t_id="115">van</token>
  <token number="19" sentence="6" t_id="116">handelaren</token>
  <token number="20" sentence="6" t_id="117">is</token>
  <token number="21" sentence="6" t_id="118">het</token>
  <token number="22" sentence="6" t_id="119">hoogtepunt</token>
  <token number="23" sentence="6" t_id="120">van</token>
  <token number="24" sentence="6" t_id="121">5.350</token>
  <token number="25" sentence="6" t_id="122">dat</token>
  <token number="26" sentence="6" t_id="123">we</token>
  <token number="27" sentence="6" t_id="124">in</token>
  <token number="28" sentence="6" t_id="125">september</token>
  <token number="29" sentence="6" t_id="126">vorig</token>
  <token number="30" sentence="6" t_id="127">jaar</token>
  <token number="31" sentence="6" t_id="128">haalden</token>
  <token number="32" sentence="6" t_id="129">en</token>
  <token number="33" sentence="6" t_id="130">dat</token>
  <token number="34" sentence="6" t_id="131">zou</token>
  <token number="35" sentence="6" t_id="132">me</token>
  <token number="36" sentence="6" t_id="133">deze</token>
  <token number="37" sentence="6" t_id="134">week</token>
  <token number="38" sentence="6" t_id="135">niet</token>
  <token number="39" sentence="6" t_id="136">verbazen</token>
  <token number="40" sentence="6" t_id="137">zoals</token>
  <token number="41" sentence="6" t_id="138">het</token>
  <token number="42" sentence="6" t_id="139">er</token>
  <token number="43" sentence="6" t_id="140">nu</token>
  <token number="44" sentence="6" t_id="141">uitziet</token>
  <token number="45" sentence="6" t_id="142">.</token>
  <token number="46" sentence="6" t_id="143">'</token>
  <token number="47" sentence="6" t_id="144">'</token>
  <token number="0" sentence="7" t_id="145">Ook</token>
  <token number="1" sentence="7" t_id="146">andere</token>
  <token number="2" sentence="7" t_id="147">Europese</token>
  <token number="3" sentence="7" t_id="148">markten</token>
  <token number="4" sentence="7" t_id="149">noteerden</token>
  <token number="5" sentence="7" t_id="150">maandag</token>
  <token number="6" sentence="7" t_id="151">winst</token>
  <token number="7" sentence="7" t_id="152">.</token>
  <token number="0" sentence="8" t_id="153">De</token>
  <token number="1" sentence="8" t_id="154">Duitse</token>
  <token number="2" sentence="8" t_id="155">DAX-index</token>
  <token number="3" sentence="8" t_id="156">steeg</token>
  <token number="4" sentence="8" t_id="157">71,35</token>
  <token number="5" sentence="8" t_id="158">punten</token>
  <token number="6" sentence="8" t_id="159">tot</token>
  <token number="7" sentence="8" t_id="160">5.783,23</token>
  <token number="8" sentence="8" t_id="161">terwijl</token>
  <token number="9" sentence="8" t_id="162">de</token>
  <token number="10" sentence="8" t_id="163">Franse</token>
  <token number="11" sentence="8" t_id="164">CAC</token>
  <token number="12" sentence="8" t_id="165">40</token>
  <token number="13" sentence="8" t_id="166">met</token>
  <token number="14" sentence="8" t_id="167">46,19</token>
  <token number="15" sentence="8" t_id="168">opklom</token>
  <token number="16" sentence="8" t_id="169">tot</token>
  <token number="17" sentence="8" t_id="170">3.845,8</token>
  <token number="18" sentence="8" t_id="171">.</token>
  <Markables>
    <C-SIGNAL comment="" m_id="57">
      <token_anchor t_id="72"/>
    </C-SIGNAL>
    <ENTITY_MENTION comment="" head="" m_id="36" syntactic_type="">
      <token_anchor t_id="82"/>
      <token_anchor t_id="83"/>
      <token_anchor t_id="80"/>
      <token_anchor t_id="81"/>
    </ENTITY_MENTION>
    <ENTITY_MENTION comment="" head="" m_id="37" syntactic_type="NAM">
      <token_anchor t_id="86"/>
      <token_anchor t_id="87"/>
    </ENTITY_MENTION>
    <ENTITY_MENTION comment="" head="" m_id="48" syntactic_type="PRE.NAM">
      <token_anchor t_id="11"/>
    </ENTITY_MENTION>
    <ENTITY_MENTION comment="" head="" m_id="24" syntactic_type="NAM">
      <token_anchor t_id="1"/>
      <token_anchor t_id="2"/>
    </ENTITY_MENTION>
    <ENTITY_MENTION comment="" head="" m_id="25" syntactic_type="">
      <token_anchor t_id="8"/>
      <token_anchor t_id="5"/>
      <token_anchor t_id="4"/>
      <token_anchor t_id="7"/>
      <token_anchor t_id="6"/>
    </ENTITY_MENTION>
    <ENTITY_MENTION comment="" head="" m_id="26" syntactic_type="">
      <token_anchor t_id="11"/>
      <token_anchor t_id="10"/>
      <token_anchor t_id="12"/>
    </ENTITY_MENTION>
    <ENTITY_MENTION comment="" head="" m_id="27" syntactic_type="">
      <token_anchor t_id="19"/>
      <token_anchor t_id="18"/>
      <token_anchor t_id="15"/>
      <token_anchor t_id="17"/>
      <token_anchor t_id="16"/>
    </ENTITY_MENTION>
    <ENTITY_MENTION comment="" head="" m_id="28" syntactic_type="PRE.NAM">
      <token_anchor t_id="16"/>
    </ENTITY_MENTION>
    <ENTITY_MENTION comment="" head="" m_id="29" syntactic_type="NAM">
      <token_anchor t_id="19"/>
      <token_anchor t_id="18"/>
    </ENTITY_MENTION>
    <ENTITY_MENTION comment="" head="" m_id="30" syntactic_type="">
      <token_anchor t_id="24"/>
      <token_anchor t_id="25"/>
      <token_anchor t_id="26"/>
      <token_anchor t_id="27"/>
      <token_anchor t_id="23"/>
      <token_anchor t_id="28"/>
    </ENTITY_MENTION>
    <ENTITY_MENTION comment="" head="" m_id="31" syntactic_type="">
      <token_anchor t_id="31"/>
      <token_anchor t_id="30"/>
    </ENTITY_MENTION>
    <ENTITY_MENTION comment="" head="" m_id="32" syntactic_type="">
      <token_anchor t_id="36"/>
      <token_anchor t_id="35"/>
    </ENTITY_MENTION>
    <ENTITY_MENTION comment="" head="" m_id="33" syntactic_type="NAM">
      <token_anchor t_id="60"/>
      <token_anchor t_id="61"/>
      <token_anchor t_id="62"/>
    </ENTITY_MENTION>
    <ENTITY_MENTION comment="" head="" m_id="34" syntactic_type="">
      <token_anchor t_id="64"/>
      <token_anchor t_id="65"/>
      <token_anchor t_id="66"/>
    </ENTITY_MENTION>
    <ENTITY_MENTION comment="" head="" m_id="35" syntactic_type="">
      <token_anchor t_id="75"/>
      <token_anchor t_id="74"/>
      <token_anchor t_id="73"/>
    </ENTITY_MENTION>
    <EVENT_MENTION aspect="NONE" certainty="CERTAIN" comment="" m_id="1" modality="" polarity="POS" pos="VERB" pred="bereiken" special_cases="NONE" tense="PRESENT" time="NON_FUTURE">
      <token_anchor t_id="3"/>
    </EVENT_MENTION>
    <EVENT_MENTION aspect="NONE" certainty="CERTAIN" comment="" m_id="2" modality="" polarity="POS" pos="VERB" pred="stijgen" special_cases="NONE" tense="PRESENT" time="NON_FUTURE">
      <token_anchor t_id="13"/>
    </EVENT_MENTION>
    <EVENT_MENTION aspect="NONE" certainty="CERTAIN" comment="" m_id="3" modality="" polarity="POS" pos="VERB" pred="sluiten" special_cases="NONE" tense="PAST" time="NON_FUTURE">
      <token_anchor t_id="20"/>
    </EVENT_MENTION>
    <EVENT_MENTION aspect="NONE" certainty="CERTAIN" comment="" m_id="4" modality="" polarity="POS" pos="VERB" pred="aankondigen" special_cases="NONE" tense="PAST" time="NON_FUTURE">
      <token_anchor t_id="33"/>
    </EVENT_MENTION>
    <EVENT_MENTION aspect="NONE" certainty="CERTAIN" comment="" m_id="5" modality="" polarity="POS" pos="VERB" pred="stijgen" special_cases="NONE" tense="PAST" time="NON_FUTURE">
      <token_anchor t_id="37"/>
    </EVENT_MENTION>
    <EVENT_MENTION aspect="NONE" certainty="CERTAIN" comment="" m_id="6" modality="" polarity="POS" pos="VERB" pred="afsluiten" special_cases="NONE" tense="PAST" time="NON_FUTURE">
      <token_anchor t_id="47"/>
      <token_anchor t_id="44"/>
    </EVENT_MENTION>
    <EVENT_MENTION aspect="NONE" certainty="CERTAIN" comment="" m_id="7" modality="" polarity="POS" pos="VERB" pred="gebeuren" special_cases="NONE" tense="PRESENT" time="NON_FUTURE">
      <token_anchor t_id="55"/>
    </EVENT_MENTION>
    <EVENT_MENTION aspect="NONE" certainty="CERTAIN" comment="" m_id="8" modality="" polarity="POS" pos="VERB" pred="noteren" special_cases="NONE" tense="PAST" time="NON_FUTURE">
      <token_anchor t_id="63"/>
    </EVENT_MENTION>
    <EVENT_MENTION aspect="NONE" certainty="CERTAIN" comment="" m_id="9" modality="" polarity="POS" pos="VERB" pred="bereiken" special_cases="NONE" tense="PAST" time="NON_FUTURE">
      <token_anchor t_id="71"/>
    </EVENT_MENTION>
    <EVENT_MENTION aspect="NONE" certainty="CERTAIN" comment="" m_id="10" modality="" polarity="POS" pos="VERB" pred="denken" special_cases="NONE" tense="PRESENT" time="NON_FUTURE">
      <token_anchor t_id="84"/>
    </EVENT_MENTION>
    <EVENT_MENTION aspect="NONE" certainty="POSSIBLE" comment="" m_id="11" modality="kan" polarity="POS" pos="VERB" pred="blijven" special_cases="NONE" tense="NONE" time="FUTURE">
      <token_anchor t_id="94"/>
    </EVENT_MENTION>
    <EVENT_MENTION aspect="NONE" certainty="POSSIBLE" comment="" m_id="12" modality="" polarity="POS" pos="VERB" pred="stijgen" special_cases="NONE" tense="INFINITIVE" time="FUTURE">
      <token_anchor t_id="95"/>
    </EVENT_MENTION>
    <SIGNAL comment="" m_id="62">
      <token_anchor t_id="6"/>
    </SIGNAL>
    <SIGNAL comment="" m_id="63">
      <token_anchor t_id="29"/>
    </SIGNAL>
    <SIGNAL comment="" m_id="64">
      <token_anchor t_id="26"/>
    </SIGNAL>
    <SIGNAL comment="" m_id="65">
      <token_anchor t_id="56"/>
    </SIGNAL>
    <SIGNAL comment="" m_id="66">
      <token_anchor t_id="76"/>
    </SIGNAL>
    <TIMEX3 anchorTimeID="" beginPoint="" comment="" endPoint="51" functionInDocument="NONE" m_id="49" type="DURATION" value="P1Y">
      <token_anchor t_id="8"/>
      <token_anchor t_id="7"/>
    </TIMEX3>
    <TIMEX3 anchorTimeID="50" beginPoint="" comment="" endPoint="" functionInDocument="CREATION_TIME" m_id="50" type="DATE" value="2009-10-12">
      <token_anchor t_id="14"/>
    </TIMEX3>
    <TIMEX3 anchorTimeID="50" beginPoint="" comment="" endPoint="" functionInDocument="NONE" m_id="51" type="DATE" value="2009-10-12">
      <token_anchor t_id="21"/>
    </TIMEX3>
    <TIMEX3 anchorTimeID="" beginPoint="" comment="" endPoint="51" functionInDocument="NONE" m_id="52" type="DURATION" value="P1Y">
      <token_anchor t_id="27"/>
      <token_anchor t_id="28"/>
    </TIMEX3>
    <TIMEX3 anchorTimeID="50" beginPoint="" comment="" endPoint="" functionInDocument="NONE" m_id="53" type="DATE" value="2009-10-12">
      <token_anchor t_id="46"/>
      <token_anchor t_id="45"/>
    </TIMEX3>
    <TIMEX3 anchorTimeID="" beginPoint="" comment="" endPoint="" functionInDocument="NONE" m_id="54" type="DATE" value="2009-09">
      <token_anchor t_id="57"/>
      <token_anchor t_id="58"/>
    </TIMEX3>
    <TIMEX3 anchorTimeID="" beginPoint="" comment="" endPoint="51" functionInDocument="NONE" m_id="55" type="DURATION" value="P16M">
      <token_anchor t_id="77"/>
      <token_anchor t_id="78"/>
    </TIMEX3>
    <TIMEX3 anchorTimeID="50" beginPoint="" comment="" endPoint="" functionInDocument="NONE" m_id="56" type="DATE" value="2009-W42">
      <token_anchor t_id="91"/>
      <token_anchor t_id="90"/>
      <token_anchor t_id="88"/>
      <token_anchor t_id="89"/>
      <token_anchor t_id="92"/>
    </TIMEX3>
    <VALUE comment="" m_id="58" type="QUANTITY">
      <token_anchor t_id="38"/>
    </VALUE>
    <VALUE comment="" m_id="59" type="PERCENT">
      <token_anchor t_id="42"/>
      <token_anchor t_id="41"/>
    </VALUE>
    <VALUE comment="" m_id="60" type="QUANTITY">
      <token_anchor t_id="49"/>
    </VALUE>
    <VALUE comment="" m_id="61" type="PERCENT">
      <token_anchor t_id="68"/>
      <token_anchor t_id="69"/>
    </VALUE>
    <EVENT TAG_DESCRIPTOR="stijgen" class="OTHER" comment="" external_ref="" m_id="13"/>
    <EVENT TAG_DESCRIPTOR="blijven" class="GRAMMATICAL" comment="" external_ref="" m_id="14"/>
    <EVENT TAG_DESCRIPTOR="denkt" class="SPEECH_COGNITIVE" comment="" external_ref="" m_id="15"/>
    <EVENT TAG_DESCRIPTOR="noteerde" class="OTHER" comment="" external_ref="" m_id="16"/>
    <EVENT TAG_DESCRIPTOR="gebeurd" class="OTHER" comment="" external_ref="" m_id="17"/>
    <EVENT TAG_DESCRIPTOR="alsluiten" class="OTHER" comment="" external_ref="" m_id="18"/>
    <EVENT TAG_DESCRIPTOR="steeg s3" class="OTHER" comment="" external_ref="" m_id="19"/>
    <EVENT TAG_DESCRIPTOR="aangekondigd" class="SPEECH_COGNITIVE" comment="" external_ref="" m_id="20"/>
    <EVENT TAG_DESCRIPTOR="stijgen" class="OTHER" comment="" external_ref="" m_id="21"/>
    <EVENT TAG_DESCRIPTOR="bereiken hoogste punt" class="OTHER" comment="" external_ref="" m_id="22"/>
    <EVENT TAG_DESCRIPTOR="sloot" class="OTHER" comment="" external_ref="" m_id="23"/>
    <ENTITY TAG_DESCRIPTOR="hoogste koers" comment="" ent_class="" ent_type="FIN" external_ref="" m_id="38"/>
    <ENTITY TAG_DESCRIPTOR="hoogste stijging " comment="" ent_class="" ent_type="PRO" external_ref="" m_id="39"/>
    <ENTITY TAG_DESCRIPTOR="old mutual " comment="" ent_class="" ent_type="ORG" external_ref="" m_id="40"/>
    <ENTITY TAG_DESCRIPTOR="betere grondstofprijzen " comment="" ent_class="" ent_type="FIN" external_ref="" m_id="41"/>
    <ENTITY TAG_DESCRIPTOR="britse " comment="" ent_class="" ent_type="LOC" external_ref="" m_id="42"/>
    <ENTITY TAG_DESCRIPTOR="Europa " comment="" ent_class="" ent_type="LOC" external_ref="" m_id="43"/>
    <ENTITY TAG_DESCRIPTOR="andere europese beurzen " comment="" ent_class="" ent_type="FIN" external_ref="" m_id="44"/>
    <ENTITY TAG_DESCRIPTOR="hoogste punt in een jaar " comment="" ent_class="" ent_type="PRO" external_ref="" m_id="45"/>
    <ENTITY TAG_DESCRIPTOR="FTSE100" comment="" ent_class="" ent_type="FIN" external_ref="" m_id="46"/>
    <ENTITY TAG_DESCRIPTOR="een aantal economisch analisten " comment="" ent_class="" ent_type="PER" external_ref="" m_id="47"/>
  </Markables>
  <Relations>
    
    
    
    
    
    
    
    
    
    
    
    
    
    
    
    
    
    
    
    
    
    <SLINK r_id="269955">
      <source m_id="10"/>
      <target m_id="11"/>
    </SLINK>
    <GLINK r_id="269956">
      <source m_id="11"/>
      <target m_id="12"/>
    </GLINK>
    <HAS_PARTICIPANT comment="" frame="" frame_element="" r_id="270926" sem_role="Arg1" sem_role_framework="PROPBANK">
      <source m_id="6"/>
      <target m_id="32"/>
    </HAS_PARTICIPANT>
    <HAS_PARTICIPANT comment="" frame="" frame_element="" r_id="270927" sem_role="Argm-OTHER" sem_role_framework="PROPBANK">
      <source m_id="6"/>
      <target m_id="60"/>
    </HAS_PARTICIPANT>
    <HAS_PARTICIPANT comment="" frame="" frame_element="" r_id="270928" sem_role="Arg1" sem_role_framework="PROPBANK">
      <source m_id="2"/>
      <target m_id="26"/>
    </HAS_PARTICIPANT>
    <HAS_PARTICIPANT comment="" frame="" frame_element="" r_id="270929" sem_role="Arg1" sem_role_framework="PROPBANK">
      <source m_id="3"/>
      <target m_id="27"/>
    </HAS_PARTICIPANT>
    <HAS_PARTICIPANT comment="" frame="" frame_element="" r_id="270930" sem_role="Argm-OTHER" sem_role_framework="PROPBANK">
      <source m_id="3"/>
      <target m_id="30"/>
    </HAS_PARTICIPANT>
    <HAS_PARTICIPANT comment="" frame="" frame_element="" r_id="270931" sem_role="Arg1" sem_role_framework="PROPBANK">
      <source m_id="4"/>
      <target m_id="31"/>
    </HAS_PARTICIPANT>
    <HAS_PARTICIPANT comment="" frame="" frame_element="" r_id="270932" sem_role="Arg1" sem_role_framework="PROPBANK">
      <source m_id="5"/>
      <target m_id="32"/>
    </HAS_PARTICIPANT>
    <HAS_PARTICIPANT comment="" frame="" frame_element="" r_id="270933" sem_role="Arg2" sem_role_framework="PROPBANK">
      <source m_id="5"/>
      <target m_id="58"/>
    </HAS_PARTICIPANT>
    <HAS_PARTICIPANT comment="" frame="" frame_element="" r_id="270934" sem_role="Arg2" sem_role_framework="PROPBANK">
      <source m_id="5"/>
      <target m_id="59"/>
    </HAS_PARTICIPANT>
    <HAS_PARTICIPANT comment="" frame="" frame_element="" r_id="270935" sem_role="Arg1" sem_role_framework="PROPBANK">
      <source m_id="1"/>
      <target m_id="25"/>
    </HAS_PARTICIPANT>
    <HAS_PARTICIPANT comment="" frame="" frame_element="" r_id="270936" sem_role="Arg0" sem_role_framework="PROPBANK">
      <source m_id="1"/>
      <target m_id="24"/>
    </HAS_PARTICIPANT>
    <HAS_PARTICIPANT comment="" frame="" frame_element="" r_id="270937" sem_role="Arg0" sem_role_framework="PROPBANK">
      <source m_id="8"/>
      <target m_id="33"/>
    </HAS_PARTICIPANT>
    <HAS_PARTICIPANT comment="" frame="" frame_element="" r_id="270938" sem_role="Arg1" sem_role_framework="PROPBANK">
      <source m_id="8"/>
      <target m_id="34"/>
    </HAS_PARTICIPANT>
    <HAS_PARTICIPANT comment="" frame="" frame_element="" r_id="270939" sem_role="Arg0" sem_role_framework="PROPBANK">
      <source m_id="9"/>
      <target m_id="33"/>
    </HAS_PARTICIPANT>
    <HAS_PARTICIPANT comment="" frame="" frame_element="" r_id="270940" sem_role="Arg1" sem_role_framework="PROPBANK">
      <source m_id="9"/>
      <target m_id="35"/>
    </HAS_PARTICIPANT>
    <HAS_PARTICIPANT comment="" frame="" frame_element="" r_id="270941" sem_role="Arg0" sem_role_framework="PROPBANK">
      <source m_id="10"/>
      <target m_id="36"/>
    </HAS_PARTICIPANT>
    <HAS_PARTICIPANT comment="" frame="" frame_element="" r_id="270942" sem_role="Arg1" sem_role_framework="PROPBANK">
      <source m_id="11"/>
      <target m_id="37"/>
    </HAS_PARTICIPANT>
    <HAS_PARTICIPANT comment="" frame="" frame_element="" r_id="270943" sem_role="Arg1" sem_role_framework="PROPBANK">
      <source m_id="12"/>
      <target m_id="37"/>
    </HAS_PARTICIPANT>
    <TLINK comment="" r_id="274331" reltype="SIMULTANEOUS" signalID="">
      <source m_id="50"/>
      <target m_id="51"/>
    </TLINK>
    <TLINK comment="" r_id="274332" reltype="SIMULTANEOUS" signalID="">
      <source m_id="3"/>
      <target m_id="5"/>
    </TLINK>
    <TLINK comment="" r_id="274333" reltype="ENDS" signalID="">
      <source m_id="51"/>
      <target m_id="52"/>
    </TLINK>
    <TLINK comment="" r_id="274334" reltype="SIMULTANEOUS" signalID="">
      <source m_id="51"/>
      <target m_id="53"/>
    </TLINK>
    <TLINK comment="" r_id="274335" reltype="AFTER" signalID="65">
      <source m_id="53"/>
      <target m_id="54"/>
    </TLINK>
    <TLINK comment="" r_id="274336" reltype="ENDS" signalID="">
      <source m_id="53"/>
      <target m_id="55"/>
    </TLINK>
    <TLINK comment="" r_id="274337" reltype="BEGINS" signalID="">
      <source m_id="53"/>
      <target m_id="56"/>
    </TLINK>
    <TLINK comment="" r_id="274338" reltype="IS_INCLUDED" signalID="">
      <source m_id="3"/>
      <target m_id="51"/>
    </TLINK>
    <TLINK comment="" r_id="274339" reltype="AFTER" signalID="63">
      <source m_id="3"/>
      <target m_id="4"/>
    </TLINK>
    <TLINK comment="" r_id="274348" reltype="INCLUDES" signalID="">
      <source m_id="56"/>
      <target m_id="11"/>
    </TLINK>
    <TLINK comment="" r_id="274349" reltype="BEFORE" signalID="">
      <source m_id="10"/>
      <target m_id="11"/>
    </TLINK>
    <TLINK comment="" r_id="274350" reltype="INCLUDES" signalID="">
      <source m_id="50"/>
      <target m_id="10"/>
    </TLINK>
    <TLINK comment="" r_id="274351" reltype="IS_INCLUDED" signalID="66">
      <source m_id="9"/>
      <target m_id="55"/>
    </TLINK>
    <TLINK comment="" r_id="274352" reltype="SIMULTANEOUS" signalID="">
      <source m_id="8"/>
      <target m_id="9"/>
    </TLINK>
    <TLINK comment="" r_id="274353" reltype="SIMULTANEOUS" signalID="">
      <source m_id="6"/>
      <target m_id="8"/>
    </TLINK>
    <TLINK comment="" r_id="274354" reltype="BEGUN_BY" signalID="65">
      <source m_id="7"/>
      <target m_id="54"/>
    </TLINK>
    <TLINK comment="" r_id="274355" reltype="SIMULTANEOUS" signalID="">
      <source m_id="5"/>
      <target m_id="6"/>
    </TLINK>
  <REFERS_TO r_id="263297">
<source m_id="12"/>
<target m_id="13"/>
</REFERS_TO>
<REFERS_TO r_id="263298">
<source m_id="25"/>
<source m_id="30"/>
<target m_id="45"/>
</REFERS_TO>
<REFERS_TO r_id="263299">
<source m_id="4"/>
<target m_id="20"/>
</REFERS_TO>
<REFERS_TO r_id="263300">
<source m_id="2"/>
<target m_id="21"/>
</REFERS_TO>
<REFERS_TO r_id="263301">
<source m_id="1"/>
<source m_id="9"/>
<target m_id="22"/>
</REFERS_TO>
<REFERS_TO r_id="263302">
<source m_id="3"/>
<target m_id="23"/>
</REFERS_TO>
<REFERS_TO r_id="263303">
<source m_id="5"/>
<target m_id="19"/>
</REFERS_TO>
<REFERS_TO r_id="263304">
<source m_id="6"/>
<target m_id="18"/>
</REFERS_TO>
<REFERS_TO r_id="263305">
<source m_id="26"/>
<target m_id="44"/>
</REFERS_TO>
<REFERS_TO r_id="263306">
<source m_id="8"/>
<target m_id="16"/>
</REFERS_TO>
<REFERS_TO r_id="263307">
<source m_id="28"/>
<target m_id="42"/>
</REFERS_TO>
<REFERS_TO r_id="263308">
<source m_id="48"/>
<target m_id="43"/>
</REFERS_TO>
<REFERS_TO r_id="263309">
<source m_id="33"/>
<target m_id="40"/>
</REFERS_TO>
<REFERS_TO r_id="263310">
<source m_id="31"/>
<target m_id="41"/>
</REFERS_TO>
<REFERS_TO r_id="263311">
<source m_id="24"/>
<source m_id="27"/>
<source m_id="29"/>
<source m_id="32"/>
<target m_id="46"/>
</REFERS_TO>
<REFERS_TO r_id="263312">
<source m_id="35"/>
<target m_id="38"/>
</REFERS_TO>
<REFERS_TO r_id="263313">
<source m_id="7"/>
<target m_id="17"/>
</REFERS_TO>
<REFERS_TO r_id="263314">
<source m_id="36"/>
<target m_id="47"/>
</REFERS_TO>
<REFERS_TO r_id="263315">
<source m_id="10"/>
<target m_id="15"/>
</REFERS_TO>
<REFERS_TO r_id="263316">
<source m_id="34"/>
<target m_id="39"/>
</REFERS_TO>
<REFERS_TO r_id="263317">
<source m_id="11"/>
<target m_id="14"/>
</REFERS_TO>
</Relations>
</Document>